AUTHORS
LICENSE
MANIFEST.in
README.rst
setup.cfg
setup.py
django_trackstats.egg-info/PKG-INFO
django_trackstats.egg-info/SOURCES.txt
django_trackstats.egg-info/dependency_links.txt
django_trackstats.egg-info/not-zip-safe
django_trackstats.egg-info/requires.txt
django_trackstats.egg-info/top_level.txt
trackstats/__init__.py
trackstats/apps.py
trackstats/models.py
trackstats/trackers.py
trackstats/admin/__init__.py
trackstats/admin/forms.py
trackstats/migrations/0001_initial.py
trackstats/migrations/0002_alter_domain_id_alter_metric_id_and_more.py
trackstats/migrations/0003_alter_model_fields.py
trackstats/migrations/0004_alter_default_auto_field.py
trackstats/migrations/__init__.py
trackstats/static/trackstats/css/admin.css
trackstats/static/trackstats/js/graphs.js
trackstats/templates/trackstats/admin/graph.html
trackstats/templates/trackstats/admin/by_date/change_list.html
trackstats/templates/trackstats/admin/by_date/graph.html
trackstats/templates/trackstats/admin/by_date_and_object/change_list.html
trackstats/templates/trackstats/admin/by_date_and_object/graph.html
trackstats/tests/__init__.py
trackstats/tests/models.py
trackstats/tests/settings.py
trackstats/tests/test_models.py
trackstats/tests/test_trackers.py